latest_tweets/__init__.py
latest_tweets/admin.py
latest_tweets/apps.py
latest_tweets/models.py
latest_tweets/utils.py
latest_tweets/management/__init__.py
latest_tweets/management/commands/__init__.py
latest_tweets/management/commands/latest_tweets_auth.py
latest_tweets/management/commands/latest_tweets_update.py
latest_tweets/migrations/0001_initial.py
latest_tweets/migrations/0002_retweeted.py
latest_tweets/migrations/0003_tweet_is_reply.py
latest_tweets/migrations/0004_username_length.py
latest_tweets/migrations/0005_names.py
latest_tweets/migrations/0006_verbose_names.py
latest_tweets/migrations/0007_tweet_html.py
latest_tweets/migrations/0008_photo.py
latest_tweets/migrations/0009_counts.py
latest_tweets/migrations/0010_photo_unique.py
latest_tweets/migrations/0011_photo_image_file.py
latest_tweets/migrations/0012_likes.py
latest_tweets/migrations/0013_hashtags.py
latest_tweets/migrations/0014_display_name_length.py
latest_tweets/migrations/__init__.py
latest_tweets/templatetags/__init__.py
latest_tweets/templatetags/latest_tweets_tags.py
django_latest_tweets-0.4.7.dist-info/LICENSE
django_latest_tweets-0.4.7.dist-info/METADATA
django_latest_tweets-0.4.7.dist-info/WHEEL
django_latest_tweets-0.4.7.dist-info/top_level.txt
django_latest_tweets-0.4.7.dist-info/RECORD
