Metadata-Version: 2.1
Name: django-latest-tweets
Version: 0.4.7
Summary: Latest Tweets for Django
Home-page: https://github.com/developersociety/django-latest-tweets
Maintainer: The Developer Society
Maintainer-email: studio@dev.ngo
License: BSD
Platform: any
Classifier: Environment :: Web Environment
Classifier: Intended Audience :: Developers
Classifier: License :: OSI Approved :: BSD License
Classifier: Operating System :: OS Independent
Classifier: Programming Language :: Python
Classifier: Programming Language :: Python :: 3
Classifier: Programming Language :: Python :: 3.5
Classifier: Programming Language :: Python :: 3.6
Classifier: Programming Language :: Python :: 3.7
Classifier: Programming Language :: Python :: 3.8
Classifier: Programming Language :: Python :: 3.9
Classifier: Programming Language :: Python :: 3.10
Classifier: Framework :: Django
Classifier: Framework :: Django :: 1.11
Classifier: Framework :: Django :: 2.2
Classifier: Framework :: Django :: 3.2
Requires-Python: >=3.5
License-File: LICENSE
Requires-Dist: Django (>=1.11)
Requires-Dist: twitter (>=1.18.0)
Requires-Dist: requests (>=2.20.0)
